nfs4_share/__init__.py
nfs4_share/__main__.py
nfs4_share/acl.py
nfs4_share/cli.py
nfs4_share/htaccess.py
nfs4_share/manage.py
nfs4_share/share.py
nfs4_share/track_changes.py
nfs4_share-0.6.1.dist-info/LICENSE
nfs4_share-0.6.1.dist-info/METADATA
nfs4_share-0.6.1.dist-info/WHEEL
nfs4_share-0.6.1.dist-info/entry_points.txt
nfs4_share-0.6.1.dist-info/top_level.txt
nfs4_share-0.6.1.dist-info/RECORD
