Metadata-Version: 2.1
Name: nfs4-share
Version: 0.6.1
Summary: Share data without data duplication using nfs4_acls and hard links
Home-page: https://github.com/princessmaximacenter/network-filesystem-shares
Author: Chris van Run
Author-email: genomicscore@prinsesmaximacentrum.nl
License: MIT
Classifier: Development Status :: 2 - Pre-Alpha
Classifier: Intended Audience :: System Administrators
Classifier: Topic :: Communications :: File Sharing
Classifier: License :: OSI Approved :: MIT License
Classifier: Natural Language :: English
Classifier: Programming Language :: Python :: 3.6
Requires-Python: >=3.6.0
License-File: LICENSE
Requires-Dist: wheel
Requires-Dist: parse
Requires-Dist: GitPython
Provides-Extra: test
Requires-Dist: pytest ; extra == 'test'
Requires-Dist: pycodestyle ; extra == 'test'
